pinotify/__main__.py
pinotify/lib/graceful_actor.py
pinotify-1.0.0.dist-info/licenses/LICENSE.md
pinotify-1.0.0.dist-info/METADATA
pinotify-1.0.0.dist-info/WHEEL
pinotify-1.0.0.dist-info/top_level.txt
pinotify-1.0.0.dist-info/RECORD
